{
  "main": {
    "id": "359b380b569ed106",
    "type": "split",
    "children": [
      {
        "id": "92a3ef28b160a95a",
        "type": "tabs",
        "children": [
          {
            "id": "b48b780adcc5457d",
            "type": "leaf",
            "state": {
              "type": "markdown",
              "state": {
                "file": "Eldrheim/Modèles/Modèle de fiche de personnage.md",
                "mode": "source",
                "source": false
              },
              "icon": "lucide-file",
              "title": "Modèle de fiche de personnage"
            }
          },
          {
            "id": "c612c89406becff2",
            "type": "leaf",
            "state": {
              "type": "markdown",
              "state": {
                "file": "Eldrheim/Lieux/Eldrheim/Liste des villageois/Eira Vahl.md",
                "mode": "source",
                "source": false
              },
              "icon": "lucide-file",
              "title": "Eira Vahl"
            }
          },
          {
            "id": "dd132a9086c4ffd1",
            "type": "leaf",
            "state": {
              "type": "markdown",
              "state": {
                "file": "Eldrheim/Lieux/Eldrheim/Liste des villageois/Eira Vahl.md",
                "mode": "source",
                "source": false
              },
              "icon": "lucide-file",
              "title": "Eira Vahl"
            }
          },
          {
            "id": "4d42f827971488b2",
            "type": "leaf",
            "state": {
              "type": "markdown",
              "state": {
                "file": "Eldrheim/Lieux/Eldrheim/Liste des villageois/Halvar Drenn.md",
                "mode": "source",
                "source": false
              },
              "icon": "lucide-file",
              "title": "Halvar Drenn"
            }
          }
        ],
        "currentTab": 1
      }
    ],
    "direction": "vertical"
  },
  "left": {
    "id": "5004c36479589601",
    "type": "split",
    "children": [
      {
        "id": "91594086fa1d3524",
        "type": "tabs",
        "children": [
          {
            "id": "c99412b30eebcc23",
            "type": "leaf",
            "state": {
              "type": "file-explorer",
              "state": {
                "sortOrder": "byCreatedTime",
                "autoReveal": false
              },
              "icon": "lucide-folder-closed",
              "title": "Files"
            }
          },
          {
            "id": "d81bc069adde2f7d",
            "type": "leaf",
            "state": {
              "type": "search",
              "state": {
                "query": "couture",
                "matchingCase": false,
                "explainSearch": false,
                "collapseAll": false,
                "extraContext": false,
                "sortOrder": "alphabetical"
              },
              "icon": "lucide-search",
              "title": "Search"
            }
          },
          {
            "id": "189df9bcd08e67ea",
            "type": "leaf",
            "state": {
              "type": "bookmarks",
              "state": {},
              "icon": "lucide-bookmark",
              "title": "Bookmarks"
            }
          }
        ]
      }
    ],
    "direction": "horizontal",
    "width": 300
  },
  "right": {
    "id": "d3f62f8c58ebfa9f",
    "type": "split",
    "children": [
      {
        "id": "5b9e0cda99fb79d5",
        "type": "tabs",
        "children": [
          {
            "id": "97cf9bc4b384ab93",
            "type": "leaf",
            "state": {
              "type": "backlink",
              "state": {
                "file": "Eldrheim/Lieux/Eldrheim/Liste des villageois/Bodil Steinarsdottir.md",
                "collapseAll": false,
                "extraContext": false,
                "sortOrder": "alphabetical",
                "showSearch": false,
                "searchQuery": "",
                "backlinkCollapsed": false,
                "unlinkedCollapsed": true
              },
              "icon": "links-coming-in",
              "title": "Backlinks for Bodil Steinarsdottir"
            }
          },
          {
            "id": "31008c17ef02ffb8",
            "type": "leaf",
            "state": {
              "type": "outgoing-link",
              "state": {
                "file": "Eldrheim/Lieux/Eldrheim/Liste des villageois/Bodil Steinarsdottir.md",
                "linksCollapsed": false,
                "unlinkedCollapsed": true
              },
              "icon": "links-going-out",
              "title": "Outgoing links from Bodil Steinarsdottir"
            }
          },
          {
            "id": "a077e6ce7c7b5255",
            "type": "leaf",
            "state": {
              "type": "tag",
              "state": {
                "sortOrder": "frequency",
                "useHierarchy": true,
                "showSearch": false,
                "searchQuery": ""
              },
              "icon": "lucide-tags",
              "title": "Tags"
            }
          },
          {
            "id": "efe7f2387131a5a0",
            "type": "leaf",
            "state": {
              "type": "outline",
              "state": {
                "file": "Eldrheim/Lieux/Eldrheim/Liste des villageois/Bodil Steinarsdottir.md",
                "followCursor": false,
                "showSearch": false,
                "searchQuery": ""
              },
              "icon": "lucide-list",
              "title": "Outline of Bodil Steinarsdottir"
            }
          }
        ]
      }
    ],
    "direction": "horizontal",
    "width": 300,
    "collapsed": true
  },
  "left-ribbon": {
    "hiddenItems": {
      "switcher:Open quick switcher": false,
      "graph:Open graph view": false,
      "canvas:Create new canvas": false,
      "daily-notes:Open today's daily note": false,
      "templates:Insert template": false,
      "command-palette:Open command palette": false
    }
  },
  "active": "c99412b30eebcc23",
  "lastOpenFiles": [
    "Eldrheim/Lieux/Eldrheim/Liste des villageois/Leif Marnell.md",
    "Eldrheim/Lieux/Eldrheim/Liste des villageois/Halvar Drenn.md",
    "Eldrheim/Lieux/Eldrheim/Liste des villageois/Eira Vahl.md",
    "Eldrheim/Modèles/Modèle de fiche de personnage.md",
    "Eldrheim/Personnages/Aevi Ulfskjald.md",
    "Eldrheim/Lieux/Eldrheim/Liste des villageois/Svala Sigurddottir.md",
    "Eldrheim/Lieux/Eldrheim/Liste des villageois/Lirael de El'Solune.md",
    "Eldrheim/Lieux/Eldrheim/Liste des villageois/Sigurd Veidbjorn.md",
    "Eldrheim/Lieux/Eldrheim/Liste des villageois/Tyrek Pasplume.md",
    "Eldrheim/Lieux/Eldrheim/Liste des villageois/Aeris Faelaryn.md",
    "Eldrheim/Lieux/Eldrheim/Liste des villageois/Orm Gorgeflamme.md",
    "Eldrheim/Lieux/Eldrheim/Liste des villageois/Hildi Picgemme.md",
    "Eldrheim/Lieux/Eldrheim/Liste des villageois/Karn Dentbrisée.md",
    "Eldrheim/Lieux/Eldrheim/Liste des villageois/Drogan Gorgeflamme.md",
    "Eldrheim/Lieux/Eldrheim/Liste des villageois/Kolm.md",
    "Runar.md",
    "Eldrheim/Lieux/Eldrheim/Liste des villageois/Gunnar Torstensson.md",
    "Eldrheim/Lieux/Eldrheim/Liste des villageois/Drakka Coeurfer.md",
    "Eldrheim/Lieux/Eldrheim/Liste des villageois/Eirik Stensson.md",
    "Eldrheim/Lieux/Eldrheim/Liste des villageois/Thyra Ottesdottir.md",
    "Eldrheim/Lieux/Eldrheim/Liste des villageois/Viggo Bjornsson.md",
    "Eldrheim/Lieux/Eldrheim/Liste des villageois/Freydis Stendottir.md",
    "Eldrheim/Lieux/Eldrheim/Liste des villageois/Sten Ottesdottir.md",
    "Eldrheim/Lieux/Eldrheim/Liste des villageois/Siv Runardottir.md",
    "Eldrheim/Lieux/Eldrheim/Liste des villageois/Runar Jaktvarg.md",
    "Eldrheim/Lieux/Eldrheim/Liste des villageois/Grom Goffs.md",
    "Eldrheim/Lieux/Faille-Mousse/Liste des villageois",
    "Eldrheim/Lieux/Faille-Mousse",
    "Eldrheim/Lieux/Eldrheim/Lieux",
    "Untitled.canvas"
  ]
}